.DS_Store
delete/.DS_Store
delete/__init__.py
delete-0.3.0.dist-info/DESCRIPTION.rst
delete-0.3.0.dist-info/METADATA
delete-0.3.0.dist-info/RECORD
delete-0.3.0.dist-info/WHEEL
delete-0.3.0.dist-info/entry_points.txt
delete-0.3.0.dist-info/metadata.json
delete-0.3.0.dist-info/top_level.txt
