Metadata-Version: 2.0
Name: delete
Version: 0.3.0
Summary: Linux Trash Bin.
Home-page: https://github.com/0xorz/delete
Author: Hang Hu
Author-email: theodorehu95@gmail.com
License: MIT License
Download-URL: https://github.com/0xorz/delete/archive/{tag}.tar.gz
Keywords: linux,trash,remove
Platform: any
